[
  {
    "step": 10,
    "loss": 10.302654552459718,
    "aux_loss": 0.0,
    "lr": 0.0005
  },
  {
    "step": 20,
    "loss": 7.929385137557984,
    "aux_loss": 0.0,
    "lr": 0.001
  },
  {
    "step": 30,
    "loss": 7.6426393508911135,
    "aux_loss": 0.0,
    "lr": 0.0009444444444444445
  },
  {
    "step": 40,
    "loss": 7.093967151641846,
    "aux_loss": 0.0,
    "lr": 0.0008888888888888888
  },
  {
    "step": 50,
    "loss": 6.833533763885498,
    "aux_loss": 0.0,
    "lr": 0.0008333333333333334
  },
  {
    "step": 60,
    "loss": 6.5629236698150635,
    "aux_loss": 0.0,
    "lr": 0.0007777777777777778
  },
  {
    "step": 70,
    "loss": 6.330550861358643,
    "aux_loss": 0.0,
    "lr": 0.0007222222222222222
  },
  {
    "step": 80,
    "loss": 6.183039569854737,
    "aux_loss": 0.0,
    "lr": 0.0006666666666666666
  },
  {
    "step": 90,
    "loss": 5.976772212982178,
    "aux_loss": 0.0,
    "lr": 0.0006111111111111112
  },
  {
    "step": 100,
    "loss": 5.8669556140899655,
    "aux_loss": 0.0,
    "lr": 0.0005555555555555556
  },
  {
    "step": 110,
    "loss": 5.792183589935303,
    "aux_loss": 0.0,
    "lr": 0.0005
  },
  {
    "step": 120,
    "loss": 5.669175386428833,
    "aux_loss": 0.0,
    "lr": 0.0004444444444444444
  },
  {
    "step": 130,
    "loss": 5.6665027141571045,
    "aux_loss": 0.0,
    "lr": 0.0003888888888888889
  },
  {
    "step": 140,
    "loss": 5.497998952865601,
    "aux_loss": 0.0,
    "lr": 0.0003333333333333333
  },
  {
    "step": 150,
    "loss": 5.5081799030303955,
    "aux_loss": 0.0,
    "lr": 0.0002777777777777778
  },
  {
    "step": 160,
    "loss": 5.451082372665406,
    "aux_loss": 0.0,
    "lr": 0.0002222222222222222
  },
  {
    "step": 170,
    "loss": 5.4177011013031,
    "aux_loss": 0.0,
    "lr": 0.00016666666666666666
  },
  {
    "step": 180,
    "loss": 5.323902797698975,
    "aux_loss": 0.0,
    "lr": 0.0001111111111111111
  },
  {
    "step": 190,
    "loss": 5.33061900138855,
    "aux_loss": 0.0,
    "lr": 0.0001
  },
  {
    "step": 200,
    "loss": 5.290971040725708,
    "aux_loss": 0.0,
    "lr": 0.0001
  }
]